okapi_aether_sdk/__init__.py
okapi_aether_sdk/__version__.py
okapi_aether_sdk/aether_api.py
okapi_aether_sdk/aether_satellites_api.py
okapi_aether_sdk/aether_sensors_api.py
okapi_aether_sdk/aether_services_api.py
okapi_aether_sdk/error.py
okapi_aether_sdk/utils.py
okapi_aether_sdk/cli/__init__.py
okapi_aether_sdk/cli/aether_cli.py
okapi_aether_sdk-1.0.2.dist-info/entry_points.txt
okapi_aether_sdk-1.0.2.dist-info/licenses/LICENSE
okapi_aether_sdk-1.0.2.dist-info/WHEEL
okapi_aether_sdk-1.0.2.dist-info/METADATA
okapi_aether_sdk-1.0.2.dist-info/RECORD
